dorkbot/__init__.py
dorkbot/blocklist.py
dorkbot/database.py
dorkbot/dorkbot.py
dorkbot/target.py
dorkbot/targetdatabase.py
dorkbot/util.py
dorkbot/indexers/__init__.py
dorkbot/indexers/bing_api.py
dorkbot/indexers/commoncrawl.py
dorkbot/indexers/example.py
dorkbot/indexers/general.py
dorkbot/indexers/google_api.py
dorkbot/indexers/pywb.py
dorkbot/indexers/stdin.py
dorkbot/indexers/wayback.py
dorkbot/scanners/__init__.py
dorkbot/scanners/arachni.py
dorkbot/scanners/example.py
dorkbot/scanners/general.py
dorkbot/scanners/scnr.py
dorkbot/scanners/wapiti.py
dorkbot-1.8.0.dist-info/licenses/LICENSE
dorkbot-1.8.0.dist-info/METADATA
dorkbot-1.8.0.dist-info/WHEEL
dorkbot-1.8.0.dist-info/entry_points.txt
dorkbot-1.8.0.dist-info/top_level.txt
dorkbot-1.8.0.dist-info/RECORD
