Metadata-Version: 2.4
Name: dorkbot
Version: 1.8.0
Summary: Command-line tool to scan search results for vulnerabilities
Author-email: John Gordon <jgor@utexas.edu>
License: UT AUSTIN RESEARCH LICENSE (SOURCE CODE)
Project-URL: Homepage, http://dorkbot.io
Project-URL: GitHub, https://github.com/utiso/dorkbot
Classifier: Programming Language :: Python :: 3
Classifier: License :: Free for non-commercial use
Classifier: Operating System :: OS Independent
Requires-Python: >=3.8
License-File: LICENSE
Dynamic: license-file
